bazis/contrib/uploadable/__init__.py
bazis/contrib/uploadable/_version.py
bazis/contrib/uploadable/admin.py
bazis/contrib/uploadable/apps.py
bazis/contrib/uploadable/conf.py
bazis/contrib/uploadable/models.py
bazis/contrib/uploadable/models_abstract.py
bazis/contrib/uploadable/router.py
bazis/contrib/uploadable/routes.py
bazis/contrib/uploadable/locale/en/LC_MESSAGES/django.mo
bazis/contrib/uploadable/locale/en/LC_MESSAGES/django.po
bazis/contrib/uploadable/locale/ru/LC_MESSAGES/django.mo
bazis/contrib/uploadable/locale/ru/LC_MESSAGES/django.po
bazis/contrib/uploadable/migrations/0001_initial.py
bazis/contrib/uploadable/migrations/0002_alter_fileupload_file.py
bazis/contrib/uploadable/migrations/__init__.py
bazis_uploadable-2.2.0.dist-info/METADATA
bazis_uploadable-2.2.0.dist-info/WHEEL
bazis_uploadable-2.2.0.dist-info/top_level.txt
bazis_uploadable-2.2.0.dist-info/RECORD
